{
  "generated_at": "2026-02-18T07:16:07+00:00",
  "items": [
    {
      "kind": "skjol",
      "title": "Skjal nr. 768 - mál 174: slysatryggingar almannatrygginga (sjúkrahjálp)",
      "link": "https://www.althingi.is/altext/157/s/768.html?utm_medium=rss",
      "published": "2026-02-17",
      "summary": "Frumvarp eftir aðra umræðu. Flutningsmaður: heilbrrh."
    },
    {
      "kind": "skjol",
      "title": "Skjal nr. 767 - mál 220: faggilding o.fl. og staðlar og Staðlaráð Íslands (endurskoðun)",
      "link": "https://www.althingi.is/altext/157/s/767.html?utm_medium=rss",
      "published": "2026-02-17",
      "summary": "Lög frá Alþingi. Flutningsmaður: atvvrh."
    },
    {
      "kind": "skjol",
      "title": "Skjal nr. 765 - mál 229: verndar- og orkunýtingaráætlun og raforkulög (orkuöflunarstefna, aukin skilvirkni o.fl.)",
      "link": "https://www.althingi.is/altext/157/s/765.html?utm_medium=rss",
      "published": "2026-02-17",
      "summary": "Frumvarp eftir aðra umræðu. Flutningsmaður: umhv.- og loftslrh."
    },
    {
      "kind": "skjol",
      "title": "Skjal nr. 764 - mál 237: breyting á þingsályktun nr. 24/152 um áætlun um vernd og orkunýtingu landsvæða",
      "link": "https://www.althingi.is/altext/157/s/764.html?utm_medium=rss",
      "published": "2026-02-17",
      "summary": "Þál. í heild. Flutningsmaður: umhv.- og loftslrh."
    },
    {
      "kind": "skjol",
      "title": "Skjal nr. 763 - mál 264: aðgengi að vefsetrum og smáforritum opinberra aðila",
      "link": "https://www.althingi.is/altext/157/s/763.html?utm_medium=rss",
      "published": "2026-02-17",
      "summary": "Nefndarálit með breytingatillögu. Flutningsmaður: am"
    },
    {
      "kind": "skjol",
      "title": "Skjal nr. 762 - mál 254: framfylgd ályktana Vestnorræna ráðsins árið 2025",
      "link": "https://www.althingi.is/altext/157/s/762.html?utm_medium=rss",
      "published": "2026-02-17",
      "summary": "Nefndarálit. Flutningsmaður: ut"
    },
    {
      "kind": "skjol",
      "title": "Skjal nr. 761 - mál 451: afnám erfðafjárskatts",
      "link": "https://www.althingi.is/altext/157/s/761.html?utm_medium=rss",
      "published": "2026-02-17",
      "summary": "Þáltill.. Flutningsmaður: ÞorgS"
    },
    {
      "kind": "skjol",
      "title": "Skjal nr. 760 - mál 400: kosningalög, sveitarstjórnarlög og lögheimili og aðsetur (sveitarstjórnarkosningar í Grindavíkurbæ)",
      "link": "https://www.althingi.is/altext/157/s/760.html?utm_medium=rss",
      "published": "2026-02-16",
      "summary": "Nefndarálit. Flutningsmaður: se"
    },
    {
      "kind": "skjol",
      "title": "Skjal nr. 758 - mál 450: hlutfall erlends vinnuafls á heilbrigðisstofnunum á Íslandi og stuðningur við íslenskunám þess",
      "link": "https://www.althingi.is/altext/157/s/758.html?utm_medium=rss",
      "published": "2026-02-16",
      "summary": "Fsp. til skrifl. svars. Flutningsmaður: SER"
    },
    {
      "kind": "skjol",
      "title": "Skjal nr. 756 - mál 448: fjölskyldusameiningar",
      "link": "https://www.althingi.is/altext/157/s/756.html?utm_medium=rss",
      "published": "2026-02-16",
      "summary": "Fsp. til munnl. svars. Flutningsmaður: KGH"
    },
    {
      "kind": "skjol",
      "title": "Skjal nr. 754 - mál 446: fækkun endómetríósuaðgerða hjá Klíníkinni",
      "link": "https://www.althingi.is/altext/157/s/754.html?utm_medium=rss",
      "published": "2026-02-16",
      "summary": "Fsp. til munnl. svars. Flutningsmaður: DME"
    },
    {
      "kind": "skjol",
      "title": "Skjal nr. 744 - mál 360: synjun á umsóknum barna um alþjóðlega vernd",
      "link": "https://www.althingi.is/altext/157/s/744.html?utm_medium=rss",
      "published": "2026-02-16",
      "summary": "Svar. Flutningsmaður: dómsmrh."
    },
    {
      "kind": "skjol",
      "title": "Skjal nr. 759 - mál 112: útlendingar (afturköllun alþjóðlegrar verndar)",
      "link": "https://www.althingi.is/altext/157/s/759.html?utm_medium=rss",
      "published": "2026-02-16",
      "summary": "Lög frá Alþingi. Flutningsmaður: dómsmrh."
    },
    {
      "kind": "skjol",
      "title": "Skjal nr. 757 - mál 449: losunarheimildir",
      "link": "https://www.althingi.is/altext/157/s/757.html?utm_medium=rss",
      "published": "2026-02-16",
      "summary": "Fsp. til munnl. svars. Flutningsmaður: KGH"
    },
    {
      "kind": "skjol",
      "title": "Skjal nr. 755 - mál 447: fyrirætlanir Evrópusambandsins varðandi Ísland, Noreg og Grænland",
      "link": "https://www.althingi.is/altext/157/s/755.html?utm_medium=rss",
      "published": "2026-02-16",
      "summary": "Fsp. til munnl. svars. Flutningsmaður: IngD"
    },
    {
      "kind": "skjol",
      "title": "Skjal nr. 753 - mál 445: skattrannsóknir",
      "link": "https://www.althingi.is/altext/157/s/753.html?utm_medium=rss",
      "published": "2026-02-16",
      "summary": "Fsp. til skrifl. svars. Flutningsmaður: GHaf"
    },
    {
      "kind": "skjol",
      "title": "Skjal nr. 743 - mál 346: geðheilsuteymi heilsugæslunnar",
      "link": "https://www.althingi.is/altext/157/s/743.html?utm_medium=rss",
      "published": "2026-02-16",
      "summary": "Svar. Flutningsmaður: heilbrrh."
    },
    {
      "kind": "skjol",
      "title": "Skjal nr. 751 - mál 272: kostnaður við starfslokasamninga",
      "link": "https://www.althingi.is/altext/157/s/751.html?utm_medium=rss",
      "published": "2026-02-16",
      "summary": "Svar. Flutningsmaður: forsrh."
    },
    {
      "kind": "skjol",
      "title": "Skjal nr. 752 - mál 444: fullgilding fríverslunarsamnings milli EFTA-ríkjanna og Mercosur",
      "link": "https://www.althingi.is/altext/157/s/752.html?utm_medium=rss",
      "published": "2026-02-16",
      "summary": "Stjórnartillaga. Flutningsmaður: utanrrh."
    },
    {
      "kind": "skjol",
      "title": "Skjal nr. 749 - mál 443: Miðstöð menntunar og skólaþjónustu o.fl. (miðlægur nemendagrunnur)",
      "link": "https://www.althingi.is/altext/157/s/749.html?utm_medium=rss",
      "published": "2026-02-16",
      "summary": "Stjórnarfrumvarp. Flutningsmaður: mennta- og barnamrh."
    },
    {
      "kind": "skjol",
      "title": "Skjal nr. 747 - mál 370: eingreiðsla og Norðurlandasamningar",
      "link": "https://www.althingi.is/altext/157/s/747.html?utm_medium=rss",
      "published": "2026-02-16",
      "summary": "Svar. Flutningsmaður: samstrh."
    },
    {
      "kind": "skjol",
      "title": "Skjal nr. 746 - mál 339: norrænt samstarf",
      "link": "https://www.althingi.is/altext/157/s/746.html?utm_medium=rss",
      "published": "2026-02-16",
      "summary": "Svar. Flutningsmaður: samstrh."
    },
    {
      "kind": "skjol",
      "title": "Skjal nr. 745 - mál 336: afturköllun alþjóðlegrar verndar",
      "link": "https://www.althingi.is/altext/157/s/745.html?utm_medium=rss",
      "published": "2026-02-16",
      "summary": "Svar. Flutningsmaður: dómsmrh."
    },
    {
      "kind": "skjol",
      "title": "Skjal nr. 732 - mál 385: greiðslur til foreldra langveikra eða alvarlega fatlaðra barna",
      "link": "https://www.althingi.is/altext/157/s/732.html?utm_medium=rss",
      "published": "2026-02-16",
      "summary": "Svar. Flutningsmaður: fél.- og húsnrh."
    },
    {
      "kind": "skjol",
      "title": "Skjal nr. 742 - mál 442: bílastæðagjöld á ferðamannastöðum",
      "link": "https://www.althingi.is/altext/157/s/742.html?utm_medium=rss",
      "published": "2026-02-10",
      "summary": "Fsp. til skrifl. svars. Flutningsmaður: SER"
    },
    {
      "kind": "skjol",
      "title": "Skjal nr. 741 - mál 441: Vetraríþróttamiðstöð Íslands og þjóðarleikvangur vetraríþrótta",
      "link": "https://www.althingi.is/altext/157/s/741.html?utm_medium=rss",
      "published": "2026-02-10",
      "summary": "Fsp. til skrifl. svars. Flutningsmaður: SSK"
    },
    {
      "kind": "skjol",
      "title": "Skjal nr. 740 - mál 440: afburðanemendur",
      "link": "https://www.althingi.is/altext/157/s/740.html?utm_medium=rss",
      "published": "2026-02-10",
      "summary": "Fsp. til munnl. svars. Flutningsmaður: JPZ"
    },
    {
      "kind": "skjol",
      "title": "Skjal nr. 738 - mál 438: hæfniviðmið",
      "link": "https://www.althingi.is/altext/157/s/738.html?utm_medium=rss",
      "published": "2026-02-10",
      "summary": "Fsp. til munnl. svars. Flutningsmaður: JPZ"
    },
    {
      "kind": "skjol",
      "title": "Skjal nr. 739 - mál 439: þekkingarmiðuð aðalnámskrá",
      "link": "https://www.althingi.is/altext/157/s/739.html?utm_medium=rss",
      "published": "2026-02-10",
      "summary": "Fsp. til munnl. svars. Flutningsmaður: JPZ"
    },
    {
      "kind": "skjol",
      "title": "Skjal nr. 737 - mál 437: stofnun nýs innviðafélags",
      "link": "https://www.althingi.is/altext/157/s/737.html?utm_medium=rss",
      "published": "2026-02-10",
      "summary": "Fsp. til munnl. svars. Flutningsmaður: NMG"
    },
    {
      "kind": "skjol",
      "title": "Skjal nr. 735 - mál 435: erlent eignarhald í mikilvægum innviðum",
      "link": "https://www.althingi.is/altext/157/s/735.html?utm_medium=rss",
      "published": "2026-02-10",
      "summary": "Fsp. til skrifl. svars. Flutningsmaður: SSB"
    },
    {
      "kind": "skjol",
      "title": "Skjal nr. 734 - mál 434: stæðiskort",
      "link": "https://www.althingi.is/altext/157/s/734.html?utm_medium=rss",
      "published": "2026-02-10",
      "summary": "Fsp. til munnl. svars. Flutningsmaður: IngÞ"
    },
    {
      "kind": "skjol",
      "title": "Skjal nr. 733 - mál 433: tekjuskattur (frádráttur vegna tómstunda barna)",
      "link": "https://www.althingi.is/altext/157/s/733.html?utm_medium=rss",
      "published": "2026-02-10",
      "summary": "Frumvarp. Flutningsmaður: DME"
    },
    {
      "kind": "skjol",
      "title": "Skjal nr. 736 - mál 436: verðlagsuppfærslur",
      "link": "https://www.althingi.is/altext/157/s/736.html?utm_medium=rss",
      "published": "2026-02-10",
      "summary": "Fsp. til skrifl. svars. Flutningsmaður: NMG"
    },
    {
      "kind": "skjol",
      "title": "Skjal nr. 731 - mál 432: virðisaukaskattur (núllskattur á barnavörur)",
      "link": "https://www.althingi.is/altext/157/s/731.html?utm_medium=rss",
      "published": "2026-02-10",
      "summary": "Frumvarp. Flutningsmaður: DME"
    },
    {
      "kind": "skjol",
      "title": "Skjal nr. 730 - mál 238: brottfall laga um Heyrnar- og talmeinastöð",
      "link": "https://www.althingi.is/altext/157/s/730.html?utm_medium=rss",
      "published": "2026-02-10",
      "summary": "Nefndarálit. Flutningsmaður: vf"
    },
    {
      "kind": "skjol",
      "title": "Skjal nr. 729 - mál 283: málaferli gegn orkufyrirtækjum og styrkir til málsaðila",
      "link": "https://www.althingi.is/altext/157/s/729.html?utm_medium=rss",
      "published": "2026-02-10",
      "summary": "Skýrsla (skv. beiðni). Flutningsmaður: umhv.- og loftslrh."
    },
    {
      "kind": "skjol",
      "title": "Skjal nr. 728 - mál 431: barnalífeyrisgreiðslur",
      "link": "https://www.althingi.is/altext/157/s/728.html?utm_medium=rss",
      "published": "2026-02-10",
      "summary": "Fsp. til skrifl. svars. Flutningsmaður: RGuðb"
    },
    {
      "kind": "skjol",
      "title": "Skjal nr. 727 - mál 430: helmingamokstur",
      "link": "https://www.althingi.is/altext/157/s/727.html?utm_medium=rss",
      "published": "2026-02-10",
      "summary": "Fsp. til munnl. svars. Flutningsmaður: IngÞ"
    },
    {
      "kind": "skjol",
      "title": "Skjal nr. 725 - mál 429: endurgreidd fjárhagsaðstoð til sveitarfélaga vegna erlendra ríkisborgara",
      "link": "https://www.althingi.is/altext/157/s/725.html?utm_medium=rss",
      "published": "2026-02-10",
      "summary": "Fsp. til skrifl. svars. Flutningsmaður: DME"
    },
    {
      "kind": "skjol",
      "title": "Skjal nr. 724 - mál 428: atvinnuleysisbætur til erlendra ríkisborgara",
      "link": "https://www.althingi.is/altext/157/s/724.html?utm_medium=rss",
      "published": "2026-02-10",
      "summary": "Fsp. til skrifl. svars. Flutningsmaður: DME"
    },
    {
      "kind": "skjol",
      "title": "Skjal nr. 723 - mál 427: barnalífeyrir til erlendra ríkisborgara",
      "link": "https://www.althingi.is/altext/157/s/723.html?utm_medium=rss",
      "published": "2026-02-10",
      "summary": "Fsp. til skrifl. svars. Flutningsmaður: DME"
    },
    {
      "kind": "skjol",
      "title": "Skjal nr. 722 - mál 426: ellilífeyrir til erlendra ríkisborgara",
      "link": "https://www.althingi.is/altext/157/s/722.html?utm_medium=rss",
      "published": "2026-02-10",
      "summary": "Fsp. til skrifl. svars. Flutningsmaður: DME"
    },
    {
      "kind": "skjol",
      "title": "Skjal nr. 721 - mál 425: örorkubætur til erlendra ríkisborgara",
      "link": "https://www.althingi.is/altext/157/s/721.html?utm_medium=rss",
      "published": "2026-02-10",
      "summary": "Fsp. til skrifl. svars. Flutningsmaður: DME"
    },
    {
      "kind": "skjol",
      "title": "Skjal nr. 712 - mál 423: kostnaður við skimun eftir krabbameini í ristli og endaþarmi",
      "link": "https://www.althingi.is/altext/157/s/712.html?utm_medium=rss",
      "published": "2026-02-10",
      "summary": "Fsp. til skrifl. svars. Flutningsmaður: RGuðb"
    },
    {
      "kind": "skjol",
      "title": "Skjal nr. 726 - mál 112: útlendingar (afturköllun alþjóðlegrar verndar)",
      "link": "https://www.althingi.is/altext/157/s/726.html?utm_medium=rss",
      "published": "2026-02-09",
      "summary": "Nefndarálit. Flutningsmaður: am"
    },
    {
      "kind": "skjol",
      "title": "Skjal nr. 720 - mál 229: verndar- og orkunýtingaráætlun og raforkulög (orkuöflunarstefna, aukin skilvirkni o.fl.)",
      "link": "https://www.althingi.is/altext/157/s/720.html?utm_medium=rss",
      "published": "2026-02-09",
      "summary": "Nefndarálit með breytingatillögu. Flutningsmaður: us"
    },
    {
      "kind": "skjol",
      "title": "Skjal nr. 719 - mál 378: fjarvist frá skóla",
      "link": "https://www.althingi.is/altext/157/s/719.html?utm_medium=rss",
      "published": "2026-02-09",
      "summary": "Svar. Flutningsmaður: mennta- og barnamrh."
    },
    {
      "kind": "skjol",
      "title": "Skjal nr. 718 - mál 384: skólameistarar framhaldsskóla",
      "link": "https://www.althingi.is/altext/157/s/718.html?utm_medium=rss",
      "published": "2026-02-09",
      "summary": "Svar. Flutningsmaður: mennta- og barnamrh."
    },
    {
      "kind": "skjol",
      "title": "Skjal nr. 716 - mál 342: starfsmannamál háskóla",
      "link": "https://www.althingi.is/altext/157/s/716.html?utm_medium=rss",
      "published": "2026-02-09",
      "summary": "Svar. Flutningsmaður: mennrh."
    },
    {
      "kind": "skjol",
      "title": "Skjal nr. 717 - mál 112: útlendingar (afturköllun alþjóðlegrar verndar)",
      "link": "https://www.althingi.is/altext/157/s/717.html?utm_medium=rss",
      "published": "2026-02-05",
      "summary": "Breytingartillaga. Flutningsmaður: am"
    },
    {
      "kind": "skjol",
      "title": "Skjal nr. 709 - mál 380: fíknimeðferðarúrræði fyrir börn",
      "link": "https://www.althingi.is/altext/157/s/709.html?utm_medium=rss",
      "published": "2026-02-05",
      "summary": "Svar. Flutningsmaður: mennta- og barnamrh."
    },
    {
      "kind": "skjol",
      "title": "Skjal nr. 706 - mál 419: frítekjumörk og tekjuviðmið",
      "link": "https://www.althingi.is/altext/157/s/706.html?utm_medium=rss",
      "published": "2026-02-05",
      "summary": "Fsp. til skrifl. svars. Flutningsmaður: BergÓ"
    },
    {
      "kind": "skjol",
      "title": "Skjal nr. 707 - mál 420: biðlaun ráðherra",
      "link": "https://www.althingi.is/altext/157/s/707.html?utm_medium=rss",
      "published": "2026-02-05",
      "summary": "Fsp. til skrifl. svars. Flutningsmaður: DME"
    },
    {
      "kind": "skjol",
      "title": "Skjal nr. 705 - mál 418: einstaklingar sem dvelja ólöglega hér á landi",
      "link": "https://www.althingi.is/altext/157/s/705.html?utm_medium=rss",
      "published": "2026-02-05",
      "summary": "Fsp. til skrifl. svars. Flutningsmaður: SMás"
    },
    {
      "kind": "skjol",
      "title": "Skjal nr. 713 - mál 424: ferðir til Brussel og Washington",
      "link": "https://www.althingi.is/altext/157/s/713.html?utm_medium=rss",
      "published": "2026-02-05",
      "summary": "Fsp. til skrifl. svars. Flutningsmaður: DME"
    },
    {
      "kind": "skjol",
      "title": "Skjal nr. 711 - mál 422: lyfjakostnaður sjúklinga og Sjúkratrygginga Íslands",
      "link": "https://www.althingi.is/altext/157/s/711.html?utm_medium=rss",
      "published": "2026-02-05",
      "summary": "Fsp. til skrifl. svars. Flutningsmaður: ÓA"
    },
    {
      "kind": "skjol",
      "title": "Skjal nr. 685 - mál 293: útskrifaðir nemendur úr diplómanámi í lögreglufræðum",
      "link": "https://www.althingi.is/altext/157/s/685.html?utm_medium=rss",
      "published": "2026-02-05",
      "summary": "Svar. Flutningsmaður: dómsmrh."
    },
    {
      "kind": "skjol",
      "title": "Skjal nr. 708 - mál 379: kostnaður við starfslokasamninga",
      "link": "https://www.althingi.is/altext/157/s/708.html?utm_medium=rss",
      "published": "2026-02-05",
      "summary": "Svar. Flutningsmaður: mennta- og barnamrh."
    },
    {
      "kind": "skjol",
      "title": "Skjal nr. 694 - mál 412: atvinnuleyfi á grundvelli sérþekkingar",
      "link": "https://www.althingi.is/altext/157/s/694.html?utm_medium=rss",
      "published": "2026-02-05",
      "summary": "Fsp. til skrifl. svars. Flutningsmaður: NMG"
    },
    {
      "kind": "skjol",
      "title": "Skjal nr. 693 - mál 411: uppbygging hjúkrunarrýma",
      "link": "https://www.althingi.is/altext/157/s/693.html?utm_medium=rss",
      "published": "2026-02-05",
      "summary": "Fsp. til skrifl. svars. Flutningsmaður: NMG"
    },
    {
      "kind": "skjol",
      "title": "Skjal nr. 710 - mál 421: norrænt samstarf 2025",
      "link": "https://www.althingi.is/altext/157/s/710.html?utm_medium=rss",
      "published": "2026-02-04",
      "summary": "Skýrsla n. (frumskjal). Flutningsmaður: Norl"
    },
    {
      "kind": "skjol",
      "title": "Skjal nr. 698 - mál 416: Fríverslunarsamtök Evrópu og Evrópska efnahagssvæðið 2025",
      "link": "https://www.althingi.is/altext/157/s/698.html?utm_medium=rss",
      "published": "2026-02-03",
      "summary": "Skýrsla n. (frumskjal). Flutningsmaður: Efta"
    },
    {
      "kind": "skjol",
      "title": "Skjal nr. 703 - mál 238: brottfall laga um Heyrnar- og talmeinastöð",
      "link": "https://www.althingi.is/altext/157/s/703.html?utm_medium=rss",
      "published": "2026-02-03",
      "summary": "Nefndarálit. Flutningsmaður: vf"
    },
    {
      "kind": "skjol",
      "title": "Skjal nr. 702 - mál 256: sameining Skipulagsstofnunar og Húsnæðis- og mannvirkjastofnunar",
      "link": "https://www.althingi.is/altext/157/s/702.html?utm_medium=rss",
      "published": "2026-02-03",
      "summary": "Nefndarálit með breytingatillögu. Flutningsmaður: vf"
    },
    {
      "kind": "skjol",
      "title": "Skjal nr. 687 - mál 410: Alþjóðaþingmannasambandið 2025",
      "link": "https://www.althingi.is/altext/157/s/687.html?utm_medium=rss",
      "published": "2026-02-03",
      "summary": "Skýrsla n. (frumskjal). Flutningsmaður: Aþing"
    },
    {
      "kind": "skjol",
      "title": "Skjal nr. 704 - mál 155: almannatryggingar (launavísitala)",
      "link": "https://www.althingi.is/altext/157/s/704.html?utm_medium=rss",
      "published": "2026-02-03",
      "summary": "Nefndarálit með frávt.. Flutningsmaður: vf"
    },
    {
      "kind": "skjol",
      "title": "Skjal nr. 686 - mál 409: norðurskautsmál 2025",
      "link": "https://www.althingi.is/altext/157/s/686.html?utm_medium=rss",
      "published": "2026-02-03",
      "summary": "Skýrsla n. (frumskjal). Flutningsmaður: Nsm"
    },
    {
      "kind": "skjol",
      "title": "Skjal nr. 715 - mál 219: fullgilding samningsins um loftslagsbreytingar, viðskipti og sjálfbærni",
      "link": "https://www.althingi.is/altext/157/s/715.html?utm_medium=rss",
      "published": "2026-02-03",
      "summary": "Þál. í heild. Flutningsmaður: utanrrh."
    },
    {
      "kind": "skjol",
      "title": "Skjal nr. 714 - mál 215: stefna í varnar- og öryggismálum",
      "link": "https://www.althingi.is/altext/157/s/714.html?utm_medium=rss",
      "published": "2026-02-03",
      "summary": "Þál. í heild. Flutningsmaður: utanrrh."
    },
    {
      "kind": "skjol",
      "title": "Skjal nr. 701 - mál 237: breyting á þingsályktun nr. 24/152 um áætlun um vernd og orkunýtingu landsvæða",
      "link": "https://www.althingi.is/altext/157/s/701.html?utm_medium=rss",
      "published": "2026-02-03",
      "summary": "Nefndarálit með breytingatillögu. Flutningsmaður: us"
    },
    {
      "kind": "skjol",
      "title": "Skjal nr. 699 - mál 417: störf Norrænu ráðherranefndarinnar 2025",
      "link": "https://www.althingi.is/altext/157/s/699.html?utm_medium=rss",
      "published": "2026-02-03",
      "summary": "Skýrsla rh. (frumskjal). Flutningsmaður: samstrh."
    },
    {
      "kind": "skjol",
      "title": "Skjal nr. 700 - mál 237: breyting á þingsályktun nr. 24/152 um áætlun um vernd og orkunýtingu landsvæða",
      "link": "https://www.althingi.is/altext/157/s/700.html?utm_medium=rss",
      "published": "2026-02-03",
      "summary": "Nefndarálit með breytingatillögu. Flutningsmaður: us"
    },
    {
      "kind": "skjol",
      "title": "Skjal nr. 697 - mál 415: fjöldi örorkulífeyrisþega",
      "link": "https://www.althingi.is/altext/157/s/697.html?utm_medium=rss",
      "published": "2026-02-03",
      "summary": "Fsp. til skrifl. svars. Flutningsmaður: NMG"
    },
    {
      "kind": "skjol",
      "title": "Skjal nr. 696 - mál 414: slátrun samkvæmt trúarsiðum",
      "link": "https://www.althingi.is/altext/157/s/696.html?utm_medium=rss",
      "published": "2026-02-03",
      "summary": "Fsp. til skrifl. svars. Flutningsmaður: DME"
    },
    {
      "kind": "skjol",
      "title": "Skjal nr. 695 - mál 413: höfnun á rannsókn á afdrifum barna sem hafa verið vistuð á meðferðarheimilum",
      "link": "https://www.althingi.is/altext/157/s/695.html?utm_medium=rss",
      "published": "2026-02-03",
      "summary": "Fsp. til munnl. svars. Flutningsmaður: DME"
    },
    {
      "kind": "skjol",
      "title": "Skjal nr. 682 - mál 406: Vestnorræna ráðið 2025",
      "link": "https://www.althingi.is/altext/157/s/682.html?utm_medium=rss",
      "published": "2026-02-03",
      "summary": "Skýrsla n. (frumskjal). Flutningsmaður: Vnorþ"
    },
    {
      "kind": "skjol",
      "title": "Skjal nr. 692 - mál 114: veitingastaðir, gististaðir og skemmtanahald (skammtímaleiga, gagnaöflun og rekstrarleyfi)",
      "link": "https://www.althingi.is/altext/157/s/692.html?utm_medium=rss",
      "published": "2026-02-02",
      "summary": "Frumvarp eftir aðra umræðu. Flutningsmaður: atvvrh."
    },
    {
      "kind": "skjol",
      "title": "Skjal nr. 691 - mál 112: útlendingar (afturköllun alþjóðlegrar verndar)",
      "link": "https://www.althingi.is/altext/157/s/691.html?utm_medium=rss",
      "published": "2026-02-02",
      "summary": "Frumvarp eftir aðra umræðu. Flutningsmaður: dómsmrh."
    },
    {
      "kind": "skjol",
      "title": "Skjal nr. 690 - mál 111: sýslumaður",
      "link": "https://www.althingi.is/altext/157/s/690.html?utm_medium=rss",
      "published": "2026-02-02",
      "summary": "Lög frá Alþingi. Flutningsmaður: dómsmrh."
    },
    {
      "kind": "skjol",
      "title": "Skjal nr. 689 - mál 115: stefna í neytendamálum til ársins 2030",
      "link": "https://www.althingi.is/altext/157/s/689.html?utm_medium=rss",
      "published": "2026-02-02",
      "summary": "Þál. í heild. Flutningsmaður: atvvrh."
    },
    {
      "kind": "skjol",
      "title": "Skjal nr. 688 - mál 90: framkvæmdaáætlun í kynjajafnréttismálum fyrir árin 2026--2029",
      "link": "https://www.althingi.is/altext/157/s/688.html?utm_medium=rss",
      "published": "2026-02-02",
      "summary": "Þál. í heild. Flutningsmaður: dómsmrh."
    },
    {
      "kind": "skjol",
      "title": "Skjal nr. 681 - mál 405: NATO-þingið 2025",
      "link": "https://www.althingi.is/altext/157/s/681.html?utm_medium=rss",
      "published": "2026-02-02",
      "summary": "Skýrsla n. (frumskjal). Flutningsmaður: NATO"
    },
    {
      "kind": "skjol",
      "title": "Skjal nr. 670 - mál 397: Evrópuráðsþingið 2025",
      "link": "https://www.althingi.is/altext/157/s/670.html?utm_medium=rss",
      "published": "2026-02-02",
      "summary": "Skýrsla n. (frumskjal). Flutningsmaður: Evr"
    },
    {
      "kind": "skjol",
      "title": "Skjal nr. 683 - mál 407: ÖSE-þingið 2025",
      "link": "https://www.althingi.is/altext/157/s/683.html?utm_medium=rss",
      "published": "2026-02-02",
      "summary": "Skýrsla n. (frumskjal). Flutningsmaður: Öse"
    },
    {
      "kind": "skjol",
      "title": "Skjal nr. 684 - mál 408: vinsælir áfangastaðir ferðamanna í eigu ríkisins",
      "link": "https://www.althingi.is/altext/157/s/684.html?utm_medium=rss",
      "published": "2026-02-02",
      "summary": "Fsp. til skrifl. svars. Flutningsmaður: IAS"
    },
    {
      "kind": "skjol",
      "title": "Skjal nr. 680 - mál 404: lóðarleigusamningar",
      "link": "https://www.althingi.is/altext/157/s/680.html?utm_medium=rss",
      "published": "2026-02-02",
      "summary": "Fsp. til skrifl. svars. Flutningsmaður: IAS"
    },
    {
      "kind": "skjol",
      "title": "Skjal nr. 679 - mál 403: umferðaröryggisaðgerðir og fallvarnir",
      "link": "https://www.althingi.is/altext/157/s/679.html?utm_medium=rss",
      "published": "2026-02-02",
      "summary": "Fsp. til skrifl. svars. Flutningsmaður: IAS"
    },
    {
      "kind": "skjol",
      "title": "Skjal nr. 678 - mál 402: forkaupsréttur",
      "link": "https://www.althingi.is/altext/157/s/678.html?utm_medium=rss",
      "published": "2026-02-02",
      "summary": "Fsp. til skrifl. svars. Flutningsmaður: IAS"
    },
    {
      "kind": "skjol",
      "title": "Skjal nr. 677 - mál 401: stuðningur við rétt grænlensku þjóðarinnar til sjálfsákvörðunar",
      "link": "https://www.althingi.is/altext/157/s/677.html?utm_medium=rss",
      "published": "2026-01-29",
      "summary": "Þáltill.. Flutningsmaður: BHar"
    },
    {
      "kind": "skjol",
      "title": "Skjal nr. 676 - mál 400: kosningalög, sveitarstjórnarlög og lögheimili og aðsetur (sveitarstjórnarkosningar í Grindavíkurbæ)",
      "link": "https://www.althingi.is/altext/157/s/676.html?utm_medium=rss",
      "published": "2026-01-29",
      "summary": "Stjórnarfrumvarp. Flutningsmaður: dómsmrh."
    },
    {
      "kind": "skjol",
      "title": "Skjal nr. 672 - mál 215: stefna í varnar- og öryggismálum",
      "link": "https://www.althingi.is/altext/157/s/672.html?utm_medium=rss",
      "published": "2026-01-29",
      "summary": "Nefndarálit með breytingatillögu. Flutningsmaður: ut"
    },
    {
      "kind": "skjol",
      "title": "Skjal nr. 675 - mál 399: fjölskyldusameiningar",
      "link": "https://www.althingi.is/altext/157/s/675.html?utm_medium=rss",
      "published": "2026-01-29",
      "summary": "Fsp. til skrifl. svars. Flutningsmaður: NMG"
    },
    {
      "kind": "skjol",
      "title": "Skjal nr. 674 - mál 398: veiting ríkisborgararéttar",
      "link": "https://www.althingi.is/altext/157/s/674.html?utm_medium=rss",
      "published": "2026-01-29",
      "summary": "Lög frá Alþingi. Flutningsmaður: am"
    },
    {
      "kind": "skjol",
      "title": "Skjal nr. 673 - mál 398: veiting ríkisborgararéttar",
      "link": "https://www.althingi.is/altext/157/s/673.html?utm_medium=rss",
      "published": "2026-01-29",
      "summary": "Frumvarp nefndar. Flutningsmaður: am"
    },
    {
      "kind": "skjol",
      "title": "Skjal nr. 666 - mál 359: stjórnvaldssektir",
      "link": "https://www.althingi.is/altext/157/s/666.html?utm_medium=rss",
      "published": "2026-01-28",
      "summary": "Svar. Flutningsmaður: dómsmrh."
    },
    {
      "kind": "skjol",
      "title": "Skjal nr. 671 - mál 112: útlendingar (afturköllun alþjóðlegrar verndar)",
      "link": "https://www.althingi.is/altext/157/s/671.html?utm_medium=rss",
      "published": "2026-01-28",
      "summary": "Breytingartillaga. Flutningsmaður: BN"
    },
    {
      "kind": "skjol",
      "title": "Skjal nr. 669 - mál 362: skýrsla Evrópuþingsins um málefni Norðurslóða",
      "link": "https://www.althingi.is/altext/157/s/669.html?utm_medium=rss",
      "published": "2026-01-28",
      "summary": "Svar. Flutningsmaður: utanrrh."
    },
    {
      "kind": "skjol",
      "title": "Skjal nr. 668 - mál 364: fjárstyrkir til að skapa umræðuvettvang um kosti og galla aðildar Íslands að Evrópusambandinu",
      "link": "https://www.althingi.is/altext/157/s/668.html?utm_medium=rss",
      "published": "2026-01-28",
      "summary": "Svar. Flutningsmaður: utanrrh."
    },
    {
      "kind": "skjol",
      "title": "Skjal nr. 665 - mál 381: VIRK",
      "link": "https://www.althingi.is/altext/157/s/665.html?utm_medium=rss",
      "published": "2026-01-28",
      "summary": "Svar. Flutningsmaður: fél.- og húsnrh."
    }
  ]
}